package pkg;

import groovy.lang.GroovyObject;
import groovy.lang.MetaClass;
import groovy.transform.Generated;
import groovy.transform.Internal;
import java.beans.Transient;
import org.codehaus.groovy.runtime.BytecodeInterface8;
import org.codehaus.groovy.runtime.callsite.CallSite;

public class TestGroovyTryCatchFinally implements GroovyObject {
   @Generated
   public TestGroovyTryCatchFinally() {
      CallSite[] var1 = $getCallSiteArray();
      super();
      MetaClass var2 = this.$getStaticMetaClass();
      this.metaClass = var2;
   }

   // $VF: Could not verify finally blocks. A semaphore variable has been added to preserve control flow.
   public void test1(String x) {
      CallSite[] var2 = $getCallSiteArray();
      if (!__$stMC && !BytecodeInterface8.disabledStandardMetaClass()) {
         boolean var36 = false /* VF: Semaphore variable */;

         try {
            var36 = true;
            var2[8].call(var2[9].callGetProperty(System.class), "sout1");// 20 21
            var36 = false;
         } catch (Exception e) {
            try {
               var2[10].call(var2[11].callGetProperty(System.class), "sout2");// 23 24
            } catch (Exception e2) {
            } finally {
               ;
            }

            var36 = false;
         } finally {
            if (var36) {
               var2[14].call(var2[15].callGetProperty(System.class), "finally");// 31
            }
         }

         var2[12].call(var2[13].callGetProperty(System.class), "finally");
      } else {
         boolean var19 = false /* VF: Semaphore variable */;

         try {
            var19 = true;
            var2[0].call(var2[1].callGetProperty(System.class), "sout1");
            var19 = false;
         } catch (Exception e) {
            try {
               var2[2].call(var2[3].callGetProperty(System.class), "sout2");
            } catch (Exception e2) {// 25
            } finally {
               ;
            }

            var19 = false;
         } finally {
            if (var19) {
               var2[6].call(var2[7].callGetProperty(System.class), "finally");
            }
         }

         var2[4].call(var2[5].callGetProperty(System.class), "finally");
      }
   }// 32

   public int foo(int a) throws Exception {
      CallSite[] var2 = $getCallSiteArray();
      if (BytecodeInterface8.isOrigInt() && BytecodeInterface8.isOrigZ() && !__$stMC && !BytecodeInterface8.disabledStandardMetaClass()) {
         if (a < 1) {// 36
            throw (Throwable)var2[18].callConstructor(RuntimeException.class);// 37
         } else if (a < 5) {// 38
            return a;// 39
         } else {
            throw (Throwable)var2[19].callConstructor(Exception.class);// 42
         }
      } else if (a < 1) {
         throw (Throwable)var2[16].callConstructor(RuntimeException.class);
      } else if (a < 5) {
         return a;
      } else {
         throw (Throwable)var2[17].callConstructor(Exception.class);
      }
   }

   public int test(String param1) {
      // $VF: Couldn't be decompiled
      // Bytecode:
      // 00: nop
      // 01: invokestatic pkg/TestGroovyTryCatchFinally.$getCallSiteArray ()[Lorg/codehaus/groovy/runtime/callsite/CallSite;
      // 04: astore 2
      // 05: aload 2
      // 06: ldc 20
      // 08: aaload
      // 09: ldc java/lang/Integer
      // 0b: aload 1
      // 0c: invokeinterface org/codehaus/groovy/runtime/callsite/CallSite.call (Ljava/lang/Object;Ljava/lang/Object;)Ljava/lang/Object; 3
      // 11: invokestatic org/codehaus/groovy/runtime/typehandling/DefaultTypeTransformation.intUnbox (Ljava/lang/Object;)I
      // 14: istore 3
      // 15: nop
      // 16: aload 2
      // 17: ldc 21
      // 19: aaload
      // 1a: aload 2
      // 1b: ldc 22
      // 1d: aaload
      // 1e: ldc java/lang/System
      // 20: invokeinterface org/codehaus/groovy/runtime/callsite/CallSite.callGetProperty (Ljava/lang/Object;)Ljava/lang/Object; 2
      // 25: ldc "Finally"
      // 27: invokeinterface org/codehaus/groovy/runtime/callsite/CallSite.call (Ljava/lang/Object;Ljava/lang/Object;)Ljava/lang/Object; 3
      // 2c: pop
      // 2d: nop
      // 2e: iload 3
      // 2f: ireturn
      // 30: nop
      // 31: nop
      // 32: athrow
      // 33: astore 4
      // 35: aload 2
      // 36: ldc 23
      // 38: aaload
      // 39: aload 2
      // 3a: ldc 24
      // 3c: aaload
      // 3d: ldc java/lang/System
      // 3f: invokeinterface org/codehaus/groovy/runtime/callsite/CallSite.callGetProperty (Ljava/lang/Object;)Ljava/lang/Object; 2
      // 44: aload 2
      // 45: ldc 25
      // 47: aaload
      // 48: ldc "Error"
      // 4a: aload 4
      // 4c: invokeinterface org/codehaus/groovy/runtime/callsite/CallSite.call (Ljava/lang/Object;Ljava/lang/Object;)Ljava/lang/Object; 3
      // 51: invokeinterface org/codehaus/groovy/runtime/callsite/CallSite.call (Ljava/lang/Object;Ljava/lang/Object;)Ljava/lang/Object; 3
      // 56: pop
      // 57: nop
      // 58: goto 5b
      // 5b: aload 2
      // 5c: ldc 26
      // 5e: aaload
      // 5f: aload 2
      // 60: ldc 27
      // 62: aaload
      // 63: ldc java/lang/System
      // 65: invokeinterface org/codehaus/groovy/runtime/callsite/CallSite.callGetProperty (Ljava/lang/Object;)Ljava/lang/Object; 2
      // 6a: ldc "Finally"
      // 6c: invokeinterface org/codehaus/groovy/runtime/callsite/CallSite.call (Ljava/lang/Object;Ljava/lang/Object;)Ljava/lang/Object; 3
      // 71: pop
      // 72: goto 91
      // 75: astore 5
      // 77: aload 2
      // 78: ldc 28
      // 7a: aaload
      // 7b: aload 2
      // 7c: ldc 29
      // 7e: aaload
      // 7f: ldc java/lang/System
      // 81: invokeinterface org/codehaus/groovy/runtime/callsite/CallSite.callGetProperty (Ljava/lang/Object;)Ljava/lang/Object; 2
      // 86: ldc "Finally"
      // 88: invokeinterface org/codehaus/groovy/runtime/callsite/CallSite.call (Ljava/lang/Object;Ljava/lang/Object;)Ljava/lang/Object; 3
      // 8d: pop
      // 8e: aload 5
      // 90: athrow
      // 91: bipush -1
      // 93: invokestatic java/lang/Integer.valueOf (I)Ljava/lang/Integer;
      // 96: invokevirtual java/lang/Integer.intValue ()I
      // 99: ireturn
      // try (3 -> 12): 29 java/lang/Exception
      // try (24 -> 26): 29 java/lang/Exception
      // try (3 -> 12): 60 null
      // try (24 -> 26): 60 null
      // try (29 -> 47): 60 null
   }

   // $VF: Could not verify finally blocks. A semaphore variable has been added to preserve control flow.
   public void testEmptyCatch(String msg) {
      CallSite[] var2 = $getCallSiteArray();
      if (!__$stMC && !BytecodeInterface8.disabledStandardMetaClass()) {
         boolean var16 = false /* VF: Semaphore variable */;

         try {
            var16 = true;
            var2[36].call(var2[37].callGetProperty(System.class), msg);// 58 59
            var16 = false;
         } catch (RuntimeException ignored) {
            var16 = false;
         } finally {
            if (var16) {
               var2[40].call(var2[41].callGetProperty(System.class), "Bye");// 62
            }
         }

         var2[38].call(var2[39].callGetProperty(System.class), "Bye");
      } else {
         boolean var11 = false /* VF: Semaphore variable */;

         try {
            var11 = true;
            var2[30].call(var2[31].callGetProperty(System.class), msg);
            var11 = false;
         } catch (RuntimeException ignored) {// 60
            var11 = false;
         } finally {
            if (var11) {
               var2[34].call(var2[35].callGetProperty(System.class), "Bye");
            }
         }

         var2[32].call(var2[33].callGetProperty(System.class), "Bye");
      }
   }// 63

   @Generated
   @Internal
   @Transient
   public MetaClass getMetaClass() {
      if (this.metaClass != null) {
         return this.metaClass;
      }

      this.metaClass = this.$getStaticMetaClass();
      return this.metaClass;
   }

   @Generated
   @Internal
   public void setMetaClass(MetaClass var1) {
      this.metaClass = var1;
   }
}

class 'pkg/TestGroovyTryCatchFinally' {
   method '<init> ()V' {
      1      13
      2      13
      3      13
      4      13
      6      14
      7      14
      8      14
      9      15
      a      15
      b      15
      c      15
      d      15
      e      16
      f      16
      11      16
      12      16
      13      16
      16      17
   }

   method 'test1 (Ljava/lang/String;)V' {
      1      21
      2      21
      3      21
      4      21
      5      22
      6      22
      7      22
      8      22
      9      22
      a      22
      b      22
      c      22
      d      22
      e      22
      f      22
      10      22
      14      50
      15      50
      16      50
      17      50
      18      50
      19      50
      1a      50
      1b      50
      1c      50
      1d      50
      1e      50
      1f      50
      20      50
      21      50
      22      50
      23      50
      24      50
      25      50
      26      50
      27      50
      28      50
      29      50
      2f      54
      30      54
      31      54
      32      54
      33      54
      34      54
      35      54
      36      54
      37      54
      38      54
      39      54
      3a      54
      3b      54
      3c      54
      3d      54
      3e      54
      3f      54
      40      54
      41      54
      42      54
      43      54
      44      54
      49      55
      5b      67
      5c      67
      5d      67
      5e      67
      5f      67
      60      67
      61      67
      62      67
      63      67
      64      67
      65      67
      66      67
      67      67
      68      67
      69      67
      6a      67
      6b      67
      6c      67
      6d      67
      6e      67
      6f      67
      70      67
      77      63
      78      63
      79      63
      7a      63
      7b      63
      7c      63
      7d      63
      7e      63
      7f      63
      80      63
      81      63
      82      63
      83      63
      84      63
      85      63
      86      63
      87      63
      88      63
      89      63
      8a      63
      8b      63
      8c      63
      94      27
      95      27
      96      27
      97      27
      98      27
      99      27
      9a      27
      9b      27
      9c      27
      9d      27
      9e      27
      9f      27
      a0      27
      a1      27
      a2      27
      a3      27
      a4      27
      a5      27
      a6      27
      a7      27
      a8      27
      a9      27
      b0      31
      b1      31
      b2      31
      b3      31
      b4      31
      b5      31
      b6      31
      b7      31
      b8      31
      b9      31
      ba      31
      bb      31
      bc      31
      bd      31
      be      31
      bf      31
      c0      31
      c1      31
      c2      31
      c3      31
      c4      31
      c5      31
      ca      32
      dc      44
      dd      44
      de      44
      df      44
      e0      44
      e1      44
      e2      44
      e3      44
      e4      44
      e5      44
      e6      44
      e7      44
      e8      44
      e9      44
      ea      44
      eb      44
      ec      44
      ed      44
      ee      44
      ef      44
      f0      44
      f1      44
      f8      40
      f9      40
      fa      40
      fb      40
      fc      40
      fd      40
      fe      40
      ff      40
      100      40
      101      40
      102      40
      103      40
      104      40
      105      40
      106      40
      107      40
      108      40
      109      40
      10a      40
      10b      40
      10c      40
      10d      40
      112      69
   }

   method 'foo (I)I' {
      1      72
      2      72
      3      72
      4      72
      5      73
      6      73
      7      73
      8      73
      9      73
      a      73
      b      73
      c      73
      d      73
      e      73
      f      73
      10      73
      11      73
      12      73
      13      73
      14      73
      15      73
      16      73
      17      73
      18      73
      19      73
      1a      73
      1b      73
      1c      73
      20      81
      21      81
      22      81
      23      81
      24      81
      2a      81
      2b      81
      2c      81
      2d      82
      2e      82
      2f      82
      30      82
      31      82
      32      82
      33      82
      34      82
      35      82
      36      82
      37      82
      38      82
      39      82
      3a      82
      3b      82
      3f      83
      40      83
      41      83
      42      83
      43      83
      49      83
      4a      83
      4b      83
      4c      84
      4d      84
      51      86
      52      86
      53      86
      54      86
      55      86
      56      86
      57      86
      58      86
      59      86
      5a      86
      5b      86
      5c      86
      5d      86
      5e      86
      5f      86
      63      74
      64      74
      65      74
      66      74
      67      74
      6d      74
      6e      74
      6f      74
      70      75
      71      75
      72      75
      73      75
      74      75
      75      75
      76      75
      77      75
      78      75
      79      75
      7a      75
      7b      75
      7c      75
      7d      75
      7e      75
      82      76
      83      76
      84      76
      85      76
      86      76
      8c      76
      8d      76
      8e      76
      8f      77
      90      77
      94      79
      95      79
      96      79
      97      79
      98      79
      99      79
      9a      79
      9b      79
      9c      79
      9d      79
      9e      79
      9f      79
      a0      79
      a1      79
      a2      79
   }

   method 'testEmptyCatch (Ljava/lang/String;)V' {
      1      180
      2      180
      3      180
      4      180
      5      181
      6      181
      7      181
      8      181
      9      181
      a      181
      b      181
      c      181
      d      181
      e      181
      f      181
      10      181
      14      202
      15      202
      16      202
      17      202
      18      202
      19      202
      1a      202
      1b      202
      1c      202
      1d      202
      1e      202
      1f      202
      20      202
      21      202
      22      202
      23      202
      24      202
      25      202
      26      202
      27      202
      28      202
      2d      204
      32      212
      33      212
      34      212
      35      212
      36      212
      37      212
      38      212
      39      212
      3a      212
      3b      212
      3c      212
      3d      212
      3e      212
      3f      212
      40      212
      41      212
      42      212
      43      212
      44      212
      45      212
      46      212
      47      212
      4e      208
      4f      208
      50      208
      51      208
      52      208
      53      208
      54      208
      55      208
      56      208
      57      208
      58      208
      59      208
      5a      208
      5b      208
      5c      208
      5d      208
      5e      208
      5f      208
      60      208
      61      208
      62      208
      63      208
      6b      186
      6c      186
      6d      186
      6e      186
      6f      186
      70      186
      71      186
      72      186
      73      186
      74      186
      75      186
      76      186
      77      186
      78      186
      79      186
      7a      186
      7b      186
      7c      186
      7d      186
      7e      186
      7f      186
      84      188
      8a      196
      8b      196
      8c      196
      8d      196
      8e      196
      8f      196
      90      196
      91      196
      92      196
      93      196
      94      196
      95      196
      96      196
      97      196
      98      196
      99      196
      9a      196
      9b      196
      9c      196
      9d      196
      9e      196
      9f      196
      a6      192
      a7      192
      a8      192
      a9      192
      aa      192
      ab      192
      ac      192
      ad      192
      ae      192
      af      192
      b0      192
      b1      192
      b2      192
      b3      192
      b4      192
      b5      192
      b6      192
      b7      192
      b8      192
      b9      192
      ba      192
      bb      192
      c0      214
   }

   method 'getMetaClass ()Lgroovy/lang/MetaClass;' {
      0      220
      1      220
      2      220
      3      220
      5      220
      6      220
      7      220
      8      221
      a      224
      c      224
      d      224
      e      224
      f      224
      10      224
      11      224
      12      225
      13      225
      14      225
      15      225
      16      225
   }

   method 'setMetaClass (Lgroovy/lang/MetaClass;)V' {
      0      231
      1      231
      2      231
      3      231
      4      231
      5      232
   }
}

Lines mapping:
20 <-> 28
21 <-> 28
23 <-> 32
24 <-> 32
25 <-> 56
31 <-> 41
32 <-> 70
36 <-> 75
37 <-> 76
38 <-> 77
39 <-> 78
42 <-> 80
58 <-> 187
59 <-> 187
60 <-> 205
62 <-> 193
63 <-> 215
Not mapped:
22
29
30
40
43
61
